ducktools/jsonkit/__init__.py
ducktools/jsonkit/__init__.pyi
ducktools/jsonkit/_caching_tools.py
ducktools/jsonkit/_caching_tools.pyi
ducktools/jsonkit/py.typed
ducktools_jsonkit-0.0.3.dist-info/LICENSE
ducktools_jsonkit-0.0.3.dist-info/METADATA
ducktools_jsonkit-0.0.3.dist-info/WHEEL
ducktools_jsonkit-0.0.3.dist-info/top_level.txt
ducktools_jsonkit-0.0.3.dist-info/RECORD
